sima_cli/__init__.py
sima_cli/__main__.py
sima_cli/__version__.py
sima_cli/cli.py
sima_cli/app_zoo/__init__.py
sima_cli/app_zoo/app.py
sima_cli/app_zoo/commands.py
sima_cli/auth/__init__.py
sima_cli/auth/auth0.py
sima_cli/auth/devportal.py
sima_cli/auth/login.py
sima_cli/auth/oauth.py
sima_cli/data/resources_internal.yaml
sima_cli/data/resources_public.yaml
sima_cli/deploy_only/__init__.py
sima_cli/deploy_only/device/__init__.py
sima_cli/deploy_only/device/commands.py
sima_cli/deploy_only/mpk/__init__.py
sima_cli/deploy_only/mpk/commands.py
sima_cli/discover/__init__.py
sima_cli/discover/discover.py
sima_cli/discover/linuxll.py
sima_cli/download/__init__.py
sima_cli/download/downloader.py
sima_cli/install/__init__.py
sima_cli/install/github_assets.py
sima_cli/install/hostdriver.py
sima_cli/install/metadata_info.py
sima_cli/install/metadata_installer.py
sima_cli/install/metadata_validator.py
sima_cli/install/optiview.py
sima_cli/install/palette.py
sima_cli/install/registry.py
sima_cli/mla/meminfo.py
sima_cli/model_zoo/__init__.py
sima_cli/model_zoo/model.py
sima_cli/network/network.py
sima_cli/sdk/__init__.py
sima_cli/sdk/cmdexec.py
sima_cli/sdk/commands.py
sima_cli/sdk/config.py
sima_cli/sdk/install.py
sima_cli/sdk/preinstall.py
sima_cli/sdk/requirements.json
sima_cli/sdk/script.py
sima_cli/sdk/stop.py
sima_cli/sdk/uninstall.py
sima_cli/sdk/utils.py
sima_cli/serial/__init__.py
sima_cli/serial/serial.py
sima_cli/storage/nvme.py
sima_cli/storage/sdcard.py
sima_cli/update/__init__.py
sima_cli/update/bmaptool.py
sima_cli/update/bootimg.py
sima_cli/update/cleanlog.py
sima_cli/update/elxr.py
sima_cli/update/local.py
sima_cli/update/netboot.py
sima_cli/update/query.py
sima_cli/update/remote.py
sima_cli/update/updater.py
sima_cli/upgrade/__init__.py
sima_cli/upgrade/selfupdate.py
sima_cli/utils/__init__.py
sima_cli/utils/api_common.py
sima_cli/utils/artifactory.py
sima_cli/utils/common.py
sima_cli/utils/config.py
sima_cli/utils/config_loader.py
sima_cli-0.0.50.dist-info/licenses/LICENSE
sima_cli-0.0.50.dist-info/METADATA
sima_cli-0.0.50.dist-info/WHEEL
sima_cli-0.0.50.dist-info/entry_points.txt
sima_cli-0.0.50.dist-info/top_level.txt
sima_cli-0.0.50.dist-info/RECORD
