Metadata-Version: 2.4
Name: sima-cli
Version: 0.0.50
Summary: CLI tool for SiMa Developer Portal to download models, firmware, and apps.
Home-page: https://developer.sima.ai/
Author: SiMa.ai
Author-email: "Sima.ai" <support@sima.ai>
License-Expression: MIT
Project-URL: Homepage, https://developer.sima.ai/
Classifier: Programming Language :: Python :: 3
Classifier: Operating System :: OS Independent
Classifier: Development Status :: 3 - Alpha
Classifier: Intended Audience :: Developers
Classifier: Topic :: Software Development :: Build Tools
Classifier: Environment :: Console
Requires-Python: >=3.8
License-File: LICENSE
Requires-Dist: click>=8.0
Requires-Dist: requests>=2.25
Requires-Dist: tqdm>=4.64
Requires-Dist: pyyaml>=6.0
Requires-Dist: paramiko>=3.5.1
Requires-Dist: plotext==5.3.2
Requires-Dist: rich==14.0.0
Requires-Dist: InquirerPy==0.3.4
Requires-Dist: tftpy==0.8.6
Requires-Dist: psutil==7.0.0
Requires-Dist: huggingface_hub==0.36.0
Requires-Dist: tabulate==0.9.0
Dynamic: author
Dynamic: license-file
Dynamic: requires-python
